aliyun_ros_cli-1.0.3.data/scripts/ros
aliyun_ros_cli-1.0.3.dist-info/DESCRIPTION.rst
aliyun_ros_cli-1.0.3.dist-info/METADATA
aliyun_ros_cli-1.0.3.dist-info/RECORD
aliyun_ros_cli-1.0.3.dist-info/WHEEL
aliyun_ros_cli-1.0.3.dist-info/metadata.json
aliyun_ros_cli-1.0.3.dist-info/pbr.json
aliyun_ros_cli-1.0.3.dist-info/top_level.txt
ros/__init__.py
ros/__init__.pyc
ros/ros.conf
ros/apps/NewConfigParser.py
ros/apps/NewConfigParser.pyc
ros/apps/__init__.py
ros/apps/__init__.pyc
ros/apps/config.py
ros/apps/config.pyc
ros/apps/utils.py
ros/apps/utils.pyc
ros/others/__init__.py
ros/others/__init__.pyc
ros/others/list_events_command.py
ros/others/list_events_command.pyc
ros/others/list_regions_command.py
ros/others/list_regions_command.pyc
ros/others/userdata_command.py
ros/resources/__init__.py
ros/resources/__init__.pyc
ros/resources/describe_resource_command.py
ros/resources/describe_resource_command.pyc
ros/resources/list_resources_command.py
ros/resources/list_resources_command.pyc
ros/resources/resource_type_command.py
ros/resources/resource_type_command.pyc
ros/resources/resource_type_detail_command.py
ros/resources/resource_type_detail_command.pyc
ros/resources/resource_type_template_command.py
ros/resources/resource_type_template_command.pyc
ros/stacks/__init__.py
ros/stacks/__init__.pyc
ros/stacks/abandon_stack_command.py
ros/stacks/abandon_stack_command.pyc
ros/stacks/create_stack_command.py
ros/stacks/create_stack_command.pyc
ros/stacks/delete_stack_command.py
ros/stacks/delete_stack_command.pyc
ros/stacks/describe_stack_command.py
ros/stacks/describe_stack_command.pyc
ros/stacks/list_stacks_command.py
ros/stacks/list_stacks_command.pyc
ros/stacks/preview_stack_command.py
ros/stacks/preview_stack_command.pyc
ros/stacks/update_stack_command.py
ros/stacks/update_stack_command.pyc
ros/templates/__init__.py
ros/templates/__init__.pyc
ros/templates/get_template_command.py
ros/templates/get_template_command.pyc
ros/templates/validate_template_command.py
ros/templates/validate_template_command.pyc
