Metadata-Version: 2.0
Name: aliyun-ros-cli
Version: 1.0.3
Summary: Aliyun ros command line tools.
Home-page: UNKNOWN
Author: shenggong.wang, quming.ly
Author-email: shenggong.wang@alibaba-inc.com
License: UNKNOWN
Keywords: aliyun,ros,template,orchestration
Platform: any
Requires-Dist: aliyun-python-sdk-ros
